kicadODE/__init__.py
kicadODE/helpers.py
kicadODE-0.1.0.dist-info/LICENSE.txt
kicadODE-0.1.0.dist-info/METADATA
kicadODE-0.1.0.dist-info/WHEEL
kicadODE-0.1.0.dist-info/top_level.txt
kicadODE-0.1.0.dist-info/RECORD
