Metadata-Version: 2.1
Name: kicadODE
Version: 0.1.0
Summary: Kicad ODE solver
Author-email: Okan Demir <okndemir@gmail.com>
Maintainer-email: Okan Demir <okndemir@gmail.com>
License: GNU GENERAL PUBLIC LICENSE
Project-URL: Homepage, https://github.com/dmrokan/kicadODE/
Project-URL: Source, https://github.com/dmrokan/kicadODE/
Keywords: sample,setuptools,development
Classifier: Development Status :: 3 - Alpha
Classifier: Intended Audience :: Developers
Classifier: Topic :: Software Development :: Build Tools
Classifier: License :: OSI Approved :: MIT License
Classifier: Programming Language :: Python :: 3
Classifier: Programming Language :: Python :: 3.7
Classifier: Programming Language :: Python :: 3.8
Classifier: Programming Language :: Python :: 3.9
Classifier: Programming Language :: Python :: 3.10
Classifier: Programming Language :: Python :: 3.11
Classifier: Programming Language :: Python :: 3 :: Only
Requires-Python: >=3.7
License-File: LICENSE.txt
Provides-Extra: dev
Provides-Extra: test
